pycyapi/__init__.py
pycyapi/cli.py
pycyapi/utils.py
pycyapi/cyverse/__init__.py
pycyapi/cyverse/auth.py
pycyapi/cyverse/clients.py
pycyapi/cyverse/commands.py
pycyapi/cyverse/exceptions.py
pycyapi/tests/__init__.py
pycyapi/tests/conftest.py
pycyapi/tests/test_cli.py
pycyapi/tests/test_utils.py
pycyapi/tests/cyverse/__init__.py
pycyapi/tests/cyverse/test_client_async.py
pycyapi/tests/cyverse/test_client_sync.py
pycyapi/tests/cyverse/test_commands.py
pycyapi-0.0.13.dist-info/METADATA
pycyapi-0.0.13.dist-info/WHEEL
pycyapi-0.0.13.dist-info/entry_points.txt
pycyapi-0.0.13.dist-info/top_level.txt
pycyapi-0.0.13.dist-info/RECORD
