Metadata-Version: 2.1
Name: pycyapi
Version: 0.0.13
Summary: Python client for the CyVerse Science APIs
Home-page: https://github.com/Computational-Plant-Science/pycyapi
Author: Computational Plant Science Lab
Author-email: wbonelli@uga.edu
Maintainer: Wes Bonelli
Maintainer-email: wbonelli@uga.edu
License: BSD-3-Clause
Keywords: hpc,slurm,singularity
Classifier: Development Status :: 3 - Alpha
Classifier: Intended Audience :: Science/Research
Classifier: License :: CC0 1.0 Universal (CC0 1.0) Public Domain Dedication
Classifier: Operating System :: Microsoft :: Windows
Classifier: Operating System :: POSIX
Classifier: Operating System :: Unix
Classifier: Operating System :: MacOS
Classifier: Programming Language :: Python
Classifier: Programming Language :: Python :: 3
Classifier: Programming Language :: Python :: 3.8
Classifier: Programming Language :: Python :: 3.9
Classifier: Programming Language :: Python :: 3.10
Classifier: Programming Language :: Python :: 3.11
Classifier: Programming Language :: Python :: 3 :: Only
Requires-Python: >=3.8
Requires-Dist: click
Requires-Dist: httpx
Requires-Dist: filelock
Requires-Dist: paramiko
Requires-Dist: pyaml
Requires-Dist: python-irodsclient
Requires-Dist: requests
Requires-Dist: tenacity
Requires-Dist: tqdm
Provides-Extra: lint
Requires-Dist: black ; extra == 'lint'
Requires-Dist: flake8 ; extra == 'lint'
Requires-Dist: isort ; extra == 'lint'
Requires-Dist: pylint ; extra == 'lint'
Provides-Extra: test
Requires-Dist: black ; extra == 'test'
Requires-Dist: flake8 ; extra == 'test'
Requires-Dist: isort ; extra == 'test'
Requires-Dist: pylint ; extra == 'test'
Requires-Dist: coverage ; extra == 'test'
Requires-Dist: coveralls ; extra == 'test'
Requires-Dist: flaky ; extra == 'test'
Requires-Dist: jupyter ; extra == 'test'
Requires-Dist: jupytext ; extra == 'test'
Requires-Dist: pytest ; extra == 'test'
Requires-Dist: pytest-asyncio ; extra == 'test'
Requires-Dist: pytest-cov ; extra == 'test'
Requires-Dist: pytest-dotenv ; extra == 'test'
Requires-Dist: pytest-xdist ; extra == 'test'
